LICENSE
README.rst
setup.py
CamoTSS/__init__.py
CamoTSS/version.py
CamoTSS.egg-info/PKG-INFO
CamoTSS.egg-info/SOURCES.txt
CamoTSS.egg-info/dependency_links.txt
CamoTSS.egg-info/entry_points.txt
CamoTSS.egg-info/requires.txt
CamoTSS.egg-info/top_level.txt
CamoTSS/bin/__init__.py
CamoTSS/bin/count.py
CamoTSS/bin/reads2.py
CamoTSS/model/logistic_4feature_model.sav
CamoTSS/utils/__init__.py
CamoTSS/utils/build_ref.py
CamoTSS/utils/get_counts.py
CamoTSS/utils/get_ctss.py
CamoTSS/utils/get_inputfile_toBrie.py
CamoTSS/utils/toolbox.py