Metadata-Version: 2.1
Name: CamoTSS
Version: 0.1.7
Summary: CamoTSS: Detection alternative TSS in single cells
Home-page: https://github.com/StatBiomed/CamoTSS
Author: ['Ruiyan Hou']
Author-email: ruiyan@connect.hku.hk
License: Apache-2.0
Keywords: Transcript Start Site,single-cell RNA-seq
Requires-Python: >=3.5
Provides-Extra: docs
License-File: LICENSE
